txl_remote_terminals/__init__.py
txl_remote_terminals/main.py
txl_remote_terminals-0.3.6.dist-info/METADATA
txl_remote_terminals-0.3.6.dist-info/WHEEL
txl_remote_terminals-0.3.6.dist-info/entry_points.txt
txl_remote_terminals-0.3.6.dist-info/licenses/LICENSE.txt
txl_remote_terminals-0.3.6.dist-info/RECORD
