Metadata-Version: 2.4
Name: txl_remote_terminals
Version: 0.3.6
Summary: TXL plugin for remote terminals
Project-URL: Source, https://github.com/davidbrochart/jpterm/plugins/remote_terminals
Author-email: David Brochart <david.brochart@gmail.com>
License-Expression: MIT
License-File: LICENSE.txt
Classifier: Development Status :: 4 - Beta
Classifier: Programming Language :: Python
Classifier: Programming Language :: Python :: 3.10
Classifier: Programming Language :: Python :: 3.11
Classifier: Programming Language :: Python :: 3.12
Classifier: Programming Language :: Python :: 3.13
Classifier: Programming Language :: Python :: Implementation :: CPython
Classifier: Programming Language :: Python :: Implementation :: PyPy
Requires-Python: >=3.10
Requires-Dist: httpx-ws>=0.4.2
Requires-Dist: httpx>=0.23.1
Requires-Dist: txl==0.3.2
